{
    "fluentMethods": true,
    "relationships": [
        {
            "relationshipType": "many-to-many",
            "otherEntityRelationshipName": "users",
            "relationshipName": "projects",
            "otherEntityName": "project",
            "otherEntityField": "id",
            "ownerSide": true
        },
        {
            "relationshipType": "many-to-many",
            "otherEntityRelationshipName": "users",
            "relationshipName": "tasks",
            "otherEntityName": "task",
            "otherEntityField": "id",
            "ownerSide": true
        }
    ],
    "fields": [
        {
            "fieldName": "login",
            "fieldType": "String"
        },
        {
            "fieldName": "firstName",
            "fieldType": "String"
        },
        {
            "fieldName": "lastName",
            "fieldType": "String"
        },
        {
            "fieldName": "email",
            "fieldType": "String"
        },
        {
            "fieldName": "imageUrl",
            "fieldType": "String"
        },
        {
            "fieldName": "activated",
            "fieldType": "Boolean"
        },
        {
            "fieldName": "langKey",
            "fieldType": "String"
        },
        {
            "fieldName": "createdBy",
            "fieldType": "String"
        },
        {
            "fieldName": "createdDate",
            "fieldType": "Instant"
        },
        {
            "fieldName": "lastModifiedBy",
            "fieldType": "String"
        },
        {
            "fieldName": "lastModifiedDate",
            "fieldType": "Instant"
        }
    ],
    "changelogDate": "20171107141048",
    "dto": "yes",
    "service": "yes",
    "entityTableName": "User",
    "jpaMetamodelFiltering": false,
    "pagination": "no"
}
